kafka_utils/__init__.py
kafka_utils/main.py
kafka_utils/kafka_check/__init__.py
kafka_utils/kafka_check/main.py
kafka_utils/kafka_check/metadata_file.py
kafka_utils/kafka_check/status_code.py
kafka_utils/kafka_check/commands/__init__.py
kafka_utils/kafka_check/commands/command.py
kafka_utils/kafka_check/commands/min_isr.py
kafka_utils/kafka_check/commands/offline.py
kafka_utils/kafka_check/commands/replica_unavailability.py
kafka_utils/kafka_check/commands/replication_factor.py
kafka_utils/kafka_cluster_manager/__init__.py
kafka_utils/kafka_cluster_manager/main.py
kafka_utils/kafka_cluster_manager/cluster_info/__init__.py
kafka_utils/kafka_cluster_manager/cluster_info/broker.py
kafka_utils/kafka_cluster_manager/cluster_info/cluster_balancer.py
kafka_utils/kafka_cluster_manager/cluster_info/cluster_topology.py
kafka_utils/kafka_cluster_manager/cluster_info/display.py
kafka_utils/kafka_cluster_manager/cluster_info/error.py
kafka_utils/kafka_cluster_manager/cluster_info/genetic_balancer.py
kafka_utils/kafka_cluster_manager/cluster_info/partition.py
kafka_utils/kafka_cluster_manager/cluster_info/partition_count_balancer.py
kafka_utils/kafka_cluster_manager/cluster_info/partition_measurer.py
kafka_utils/kafka_cluster_manager/cluster_info/replication_group_parser.py
kafka_utils/kafka_cluster_manager/cluster_info/rg.py
kafka_utils/kafka_cluster_manager/cluster_info/stats.py
kafka_utils/kafka_cluster_manager/cluster_info/topic.py
kafka_utils/kafka_cluster_manager/cluster_info/util.py
kafka_utils/kafka_cluster_manager/cmds/__init__.py
kafka_utils/kafka_cluster_manager/cmds/command.py
kafka_utils/kafka_cluster_manager/cmds/decommission.py
kafka_utils/kafka_cluster_manager/cmds/preferred_replica_election.py
kafka_utils/kafka_cluster_manager/cmds/rebalance.py
kafka_utils/kafka_cluster_manager/cmds/replace.py
kafka_utils/kafka_cluster_manager/cmds/revoke_leadership.py
kafka_utils/kafka_cluster_manager/cmds/set_replication_factor.py
kafka_utils-4.1.0.dist-info/LICENSE
kafka_utils-4.1.0.dist-info/METADATA
kafka_utils-4.1.0.dist-info/WHEEL
kafka_utils-4.1.0.dist-info/top_level.txt
kafka_utils-4.1.0.dist-info/RECORD
