Metadata-Version: 2.1
Name: kafka-utils
Version: 4.1.0
Summary: Kafka management utils
Home-page: https://github.com/Yelp/kafka-utils
Author: Team Data Streams Core
Author-email: data-streams-core@yelp.com
License: Apache License 2.0
Keywords: apache kafka
Platform: UNKNOWN
Classifier: Development Status :: 4 - Beta
Classifier: License :: OSI Approved :: Apache Software License
Classifier: Programming Language :: Python
Classifier: Programming Language :: Python :: 3
Classifier: Programming Language :: Python :: 3.7
Classifier: Programming Language :: Python :: 3.8
Classifier: Environment :: Console
Classifier: Intended Audience :: Developers
Classifier: Intended Audience :: System Administrators
Classifier: Operating System :: POSIX
Classifier: Operating System :: MacOS :: MacOS X
Requires-Python: >=3.7
Requires-Dist: humanfriendly (>=4.8)
Requires-Dist: kafka-python (<1.5.0,>=1.3.2)
Requires-Dist: kazoo (<3.0.0,>=2.0)
Requires-Dist: PyYAML (>3.10)
Requires-Dist: pytz (>=2014.1)
Requires-Dist: requests-futures (>0.9.0)
Requires-Dist: paramiko (<3.0.0,>1.8.0)
Requires-Dist: requests (<3.0.0)
Requires-Dist: tenacity
Requires-Dist: typing-extensions (>=3.7.4)
